torchruntime/__init__.py
torchruntime/__main__.py
torchruntime/configuration.py
torchruntime/consts.py
torchruntime/device_db.py
torchruntime/gpu_db.py
torchruntime/gpu_pci_ids.db
torchruntime/installer.py
torchruntime/platform_detection.py
torchruntime/tests/test_configuration.py
torchruntime/tests/test_device_db.py
torchruntime/tests/test_device_db_integration.py
torchruntime/tests/test_gpu_db.py
torchruntime/tests/test_installer.py
torchruntime/tests/test_platform_detection.py
torchruntime/tests/test_torch_device_utils.py
torchruntime/utils/__init__.py
torchruntime/utils/torch_device_utils.py
torchruntime/utils/torch_test/__init__.py
torchruntime/utils/torch_test/torch_regression_tests.py
torchruntime-2.1.0.dist-info/licenses/LICENSE
torchruntime-2.1.0.dist-info/METADATA
torchruntime-2.1.0.dist-info/WHEEL
torchruntime-2.1.0.dist-info/entry_points.txt
torchruntime-2.1.0.dist-info/top_level.txt
torchruntime-2.1.0.dist-info/RECORD
