Metadata-Version: 2.4
Name: torchruntime
Version: 2.1.0
Summary: Meant for app developers. A convenient way to install and configure the appropriate version of PyTorch on the user's computer, based on the OS and GPU manufacturer and model number.
Author-email: cmdr2 <secondary.cmdr2@gmail.com>
Project-URL: Homepage, https://github.com/easydiffusion/torchruntime
Project-URL: Bug Tracker, https://github.com/easydiffusion/torchruntime/issues
Keywords: torch,ai,ml,llm,installer,runtime
Classifier: Programming Language :: Python :: 3
Classifier: License :: OSI Approved :: MIT License
Classifier: Operating System :: Microsoft :: Windows :: Windows 10
Classifier: Operating System :: Microsoft :: Windows :: Windows 11
Classifier: Operating System :: POSIX :: Linux
Classifier: Operating System :: MacOS
Requires-Python: >=3.0
License-File: LICENSE
Requires-Dist: packaging
Dynamic: license-file
Dynamic: requires-dist
